{
  "userInfos":[
    {
      "userId":"a8105f4d-2402-ee11-9f2d-4cd577e3508c",
      "fname":"Emad",
      "label":"EK",
      "isConfirmed": 1
    },
    {
      "userId":"852bde54-2402-ee11-9f2d-4cd577e3508c",
      "fname":"Yazan",
      "label":"YQ",
      "isConfirmed":null
    },
    {
      "userId":"852bde54-2401-ee11-9f2c-4cd466e3508c",
      "fname":"shady",
      "label":"SJ",
      "isConfirmed":1
    }
  ],
  "requesterIsConfirmed":null,
  "activePlaces":[
    {
      "placeDetails":"{\"html_attributions\":[],\"result\":{\"address_components\":[{\"long_name\":\"WVXC+XW8\",\"short_name\":\"WVXC+XW8\",\"types\":[\"plus_code\"]},{\"long_name\":\"Baalbeck\",\"short_name\":\"Baalbeck\",\"types\":[\"route\"]},{\"long_name\":\"Zahran\",\"short_name\":\"Zahran\",\"types\":[\"sublocality_level_1\",\"sublocality\",\"political\"]},{\"long_name\":\"Amman\",\"short_name\":\"Amman\",\"types\":[\"locality\",\"political\"]},{\"long_name\":\"Amman Governorate\",\"short_name\":\"Amman Governorate\",\"types\":[\"administrative_area_level_1\",\"political\"]},{\"long_name\":\"Jordan\",\"short_name\":\"JO\",\"types\":[\"country\",\"political\"]}],\"adr_address\":\"WVXC+XW8, <span class=\\\"street-address\\\">Baalbeck</span>, <span class=\\\"locality\\\">Amman</span>, <span class=\\\"country-name\\\">Jordan</span>\",\"business_status\":\"OPERATIONAL\",\"current_opening_hours\":{\"open_now\":true,\"periods\":[{\"close\":{\"date\":\"2023-06-04\",\"day\":0,\"time\":\"2330\"},\"open\":{\"date\":\"2023-06-04\",\"day\":0,\"time\":\"1201\"}},{\"close\":{\"date\":\"2023-06-05\",\"day\":1,\"time\":\"2330\"},\"open\":{\"date\":\"2023-06-05\",\"day\":1,\"time\":\"1201\"}},{\"close\":{\"date\":\"2023-06-06\",\"day\":2,\"time\":\"2330\"},\"open\":{\"date\":\"2023-06-06\",\"day\":2,\"time\":\"1201\"}},{\"close\":{\"date\":\"2023-06-07\",\"day\":3,\"time\":\"2330\"},\"open\":{\"date\":\"2023-06-07\",\"day\":3,\"time\":\"1201\"}},{\"close\":{\"date\":\"2023-06-08\",\"day\":4,\"time\":\"2330\"},\"open\":{\"date\":\"2023-06-08\",\"day\":4,\"time\":\"1201\"}},{\"close\":{\"date\":\"2023-06-09\",\"day\":5,\"time\":\"2330\"},\"open\":{\"date\":\"2023-06-09\",\"day\":5,\"time\":\"1201\"}},{\"close\":{\"date\":\"2023-06-03\",\"day\":6,\"time\":\"2330\"},\"open\":{\"date\":\"2023-06-03\",\"day\":6,\"time\":\"1201\"}}],\"weekday_text\":[\"Monday: 12:01 – 11:30 PM\",\"Tuesday: 12:01 – 11:30 PM\",\"Wednesday: 12:01 – 11:30 PM\",\"Thursday: 12:01 – 11:30 PM\",\"Friday: 12:01 – 11:30 PM\",\"Saturday: 12:01 – 11:30 PM\",\"Sunday: 12:01 – 11:30 PM\"]},\"delivery\":true,\"dine_in\":true,\"formatted_address\":\"WVXC+XW8, Baalbeck, Amman, Jordan\",\"formatted_phone_number\":\"07 9000 7685\",\"geometry\":{\"location\":{\"lat\":31.949909,\"lng\":35.872316},\"viewport\":{\"northeast\":{\"lat\":31.9512833302915,\"lng\":35.8737054302915},\"southwest\":{\"lat\":31.9485853697085,\"lng\":35.8710074697085}}},\"icon\":\"https://maps.gstatic.com/mapfiles/place_api/icons/v1/png_71/restaurant-71.png\",\"icon_background_color\":\"#FF9E67\",\"icon_mask_base_uri\":\"https://maps.gstatic.com/mapfiles/place_api/icons/v2/restaurant_pinlet\",\"international_phone_number\":\"+962 7 9000 7685\",\"name\":\"Soul Food\",\"opening_hours\":{\"open_now\":true,\"periods\":[{\"close\":{\"day\":0,\"time\":\"2330\"},\"open\":{\"day\":0,\"time\":\"1201\"}},{\"close\":{\"day\":1,\"time\":\"2330\"},\"open\":{\"day\":1,\"time\":\"1201\"}},{\"close\":{\"day\":2,\"time\":\"2330\"},\"open\":{\"day\":2,\"time\":\"1201\"}},{\"close\":{\"day\":3,\"time\":\"2330\"},\"open\":{\"day\":3,\"time\":\"1201\"}},{\"close\":{\"day\":4,\"time\":\"2330\"},\"open\":{\"day\":4,\"time\":\"1201\"}},{\"close\":{\"day\":5,\"time\":\"2330\"},\"open\":{\"day\":5,\"time\":\"1201\"}},{\"close\":{\"day\":6,\"time\":\"2330\"},\"open\":{\"day\":6,\"time\":\"1201\"}}],\"weekday_text\":[\"Monday: 12:01 – 11:30 PM\",\"Tuesday: 12:01 – 11:30 PM\",\"Wednesday: 12:01 – 11:30 PM\",\"Thursday: 12:01 – 11:30 PM\",\"Friday: 12:01 – 11:30 PM\",\"Saturday: 12:01 – 11:30 PM\",\"Sunday: 12:01 – 11:30 PM\"]},\"photos\":[{\"height\":3024,\"html_attributions\":[\"<a href=\\\"https://maps.google.com/maps/contrib/116421529680303628049\\\">John Georgi</a>\"],\"photo_reference\":\"AZose0n2JKcbeGIfcMgzakY2NZYcn-CCyrotPs0yT7-Dcqz3utTNMU7dZS2U1I66dgYhWdDXajYW5helj7CxPjNd4WgYsaKPCRqpP-UlThyxuC0_yxhgNxIB44gQ9mhl8EexdzLfMQRH8olhjfZCMSCqpmrSDrhVH_cb7GV7TLiam7eaumIR\",\"width\":4032},{\"height\":1440,\"html_attributions\":[\"<a href=\\\"https://maps.google.com/maps/contrib/116212107260561764288\\\">rushdi obeidat</a>\"],\"photo_reference\":\"AZose0n-Sh0Gt--rLOHzlSppmEdUto_LehfiAC1yzFDNgVj49dOrK1FrIi8s-5wq52n0JDozbULFPYO6SYkQGMpAaJyrumzdAZG4XKgrVEeY5T631N7fiAUBkYTO3xeE0y25sy4EFf0gtY6bDbd8it8mtfZVD8ZLkoOwqYw7FXJmumINQXFu\",\"width\":2560},{\"height\":4032,\"html_attributions\":[\"<a href=\\\"https://maps.google.com/maps/contrib/113010825450466524099\\\">Zachary Hubbell</a>\"],\"photo_reference\":\"AZose0kww2N9hy0HSMg-BqNqVZOf_rZCPOBE9cI9OwIMTELH4KUAN4-2l84xosbHgKBfRcveX63eAELQlHfVw8eNnLt8jIOYcLpLmLBB9tubETsh2vgJ1_vFzU5Rk39ZYp3f4WOd965yrgliL6yF0Tar3pwvL-lqfwxtIqhmg2BdJRHDT9z3\",\"width\":3024},{\"height\":4032,\"html_attributions\":[\"<a href=\\\"https://maps.google.com/maps/contrib/117131068281655719787\\\">Shahd Almahameed</a>\"],\"photo_reference\":\"AZose0kiNpL95qXUXOjYmuP5r3ODx-zHczrRsp_4jTaMLzZxoudyaQH9rh7eUo7VM1PlXNYY8O-zALBqG5WShxX3-f3RVQNGoJsIe5g8Y1FNhNYHVStnHzks3MBo9beM2gBuKXImJEtzPAC15_3-bgejWMBwoz818nKnkQs4rez0ypstVH6p\",\"width\":3024},{\"height\":4032,\"html_attributions\":[\"<a href=\\\"https://maps.google.com/maps/contrib/113010825450466524099\\\">Zachary Hubbell</a>\"],\"photo_reference\":\"AZose0mkyXgFsnXiByri_v3MTbw1EOLsVnQ3CjZZyzq9c4QpXWef-Mpjwc75XoiSS0iEZMEm8QWjAEhtcyDojMzhVNoNbOj2ly8W13L3FM4eFemaiG8Mvhw1INGcwuBoGNc954ZYiiNV2gZDC5JNJj9zukdElCKYqa03XCZki4nfFDBrbjmS\",\"width\":3024},{\"height\":4032,\"html_attributions\":[\"<a href=\\\"https://maps.google.com/maps/contrib/111869733560236865616\\\">venice bitch</a>\"],\"photo_reference\":\"AZose0ldVWyYsO8h4RJRYUeTb8S-D8Fwoo3exaxGd1rjU3ddHhB0MkBu8m50RXwpsV3-m7y9cyWSWRe1R3_iTDuprwgiKaWhC0HNF4_F4lMNVgbO7qyOT2iiVCWq7D0L_HMAHHzrS2NmtlVCL6VehfO5T-OLiYLqRvd_F7YLsK47uUHOwPIT\",\"width\":3024},{\"height\":4032,\"html_attributions\":[\"<a href=\\\"https://maps.google.com/maps/contrib/111149300476678825445\\\">Nour Alammouri</a>\"],\"photo_reference\":\"AZose0mbACYxR0TlGqcL3qmsvnbrU_ZND8yNckSvonJKiurdPJwgpUo2gDtRspVXP7RltyRFZTlv928eFAz848GLRZGA_6DWZvgCg2onCC4tG3TJWo5PdRNiCCjRNPZ3LrmppSB_4JfyYyDZU0zu_H7NNC8Gxz3h5y7TnIDKFEoQzw2adHxT\",\"width\":3024},{\"height\":4032,\"html_attributions\":[\"<a href=\\\"https://maps.google.com/maps/contrib/104704066295796716568\\\">BrokenText</a>\"],\"photo_reference\":\"AZose0kqF_R2fWfEQ_jeRF-nzPcsmH-UxWmv5ysViapueNvEm27P1h2I66zx5PT4qNgYuDKYZVZFZHznuzI9FWPiuJkpyO_NDzYDsUQjeeUNbV_Xrqq00GcHKEGkRBxc9UYAWmg5x_yrsic96NgRWGx9tzWWlMtEFMsykCW1YsC7JUZf_rp_\",\"width\":3024},{\"height\":4032,\"html_attributions\":[\"<a href=\\\"https://maps.google.com/maps/contrib/108393306404707865087\\\">b h</a>\"],\"photo_reference\":\"AZose0mJCBn0STh5xoL--VoajTPLegxVSq6OIlCmKVWlRgNI5kVXc6HqOLZUAe0nGVoc1enTI_dJkOQHH298arjlxaUbVbSXFcGYdNYhDMDP2PYyHqNE4cqOADtYnHA2UOGIb9xHLOVHd1Begger70bNrI3N2eQt8IPfUQz-upOlKMYV4E9e\",\"width\":3024},{\"height\":1799,\"html_attributions\":[\"<a href=\\\"https://maps.google.com/maps/contrib/108256855451703446558\\\">Matt Shal</a>\"],\"photo_reference\":\"AZose0lIsm5Ck5OZI8-lt3tPXjmxsYfe1QHSYJ7g9Uv3WvdoWFAb6WH4s5fG10WNQZ3yazvEw1dRpL1RwCQ13gPt-iZeMF82jUFVd5cOjclgBGp_auVBgT-7dlu2u4xr09m8DiiEqsMakmENuDg25ckhO-ac1Sm5Lk4s45ySpJ6pE5pB-Apg\",\"width\":1440}],\"place_id\":\"ChIJOX5Zj-KgHBURcCZsSZkExrs\",\"price_level\":2,\"rating\":4.2,\"reference\":\"ChIJOX5Zj-KgHBURcCZsSZkExrs\",\"reservable\":true,\"reviews\":[{\"author_name\":\"Shahd Almahameed\",\"author_url\":\"https://www.google.com/maps/contrib/117131068281655719787/reviews\",\"language\":\"en\",\"original_language\":\"en\",\"profile_photo_url\":\"https://lh3.googleusercontent.com/a-/AD_cMMSW5xZ6D560ACeZSSu721Q0OPbPhl7tT0riOoA3pnc=s128-c0x00000000-cc-rp-mo-ba4\",\"rating\":4,\"relative_time_description\":\"10 months ago\",\"text\":\"Love the place! The staff are very friendly and polite. The food is good. Portions are fine. I only think that the food menu is a bit confusing like what is considered an appetizer and what’s not… I also think that they should start serving coffee, haven’t seen any on the menu\",\"time\":1658647847,\"translated\":false},{\"author_name\":\"Dee Avi\",\"author_url\":\"https://www.google.com/maps/contrib/106607077681290970621/reviews\",\"language\":\"en\",\"original_language\":\"en\",\"profile_photo_url\":\"https://lh3.googleusercontent.com/a-/AD_cMMS3pmvzIcL_xlD3-2ocOlQK3rmotX16oody3etrDw=s128-c0x00000000-cc-rp-mo-ba5\",\"rating\":5,\"relative_time_description\":\"9 months ago\",\"text\":\"Update: i hate their food ordering process. Must have a paper menu, not all can navigate easily on a phone menu.\\n\\nCan I dare and say that the burger there was one of the best if not the best tasting burger in Jordan? How can the bread be crunchy, light and soft at the same time? Juicy delicious meat too.\\n\\nThe service was excellent,  taste was out of this world.\\n\\nI will definitely go back again. Highly recommend this place. And the staff was super friendly.\",\"time\":1659974232,\"translated\":false},{\"author_name\":\"Matt Shal\",\"author_url\":\"https://www.google.com/maps/contrib/108256855451703446558/reviews\",\"language\":\"en\",\"original_language\":\"en\",\"profile_photo_url\":\"https://lh3.googleusercontent.com/a-/AD_cMMTRzcD3U9DT3SSiTIHSeRKBAgiXxeBl0WATZCa9Vw=s128-c0x00000000-cc-rp-mo-ba4\",\"rating\":4,\"relative_time_description\":\"10 months ago\",\"text\":\"We had been craving soul food, but hadn’t been to Soul Food in a while. We were pleasantly surprised to find that the food was just as good as we remembered. We opted for Buffalo togarashi fried chicken burger & Boneless chicken bites and a few other things. The flavors of the dish were amazing and left us feeling satisfied & full!\",\"time\":1657699315,\"translated\":false},{\"author_name\":\"Yanal Touq\",\"author_url\":\"https://www.google.com/maps/contrib/104972840186126465753/reviews\",\"language\":\"en\",\"original_language\":\"en\",\"profile_photo_url\":\"https://lh3.googleusercontent.com/a-/AD_cMMTFuTC3qAqAzROoXTI5JR0kKyPY8drm6JvnxB0MqQ=s128-c0x00000000-cc-rp-mo-ba5\",\"rating\":5,\"relative_time_description\":\"a year ago\",\"text\":\"Comfort food with a twist, Good flavor profiles, fast and friendly service. Pricing is fair considering: (arab bank customers get a 15% discount) Note: metal seats NOT comfortable at all (almost considered a 4 star rating because of that).\",\"time\":1644687222,\"translated\":false},{\"author_name\":\"BrokenText\",\"author_url\":\"https://www.google.com/maps/contrib/104704066295796716568/reviews\",\"language\":\"en\",\"original_language\":\"en\",\"profile_photo_url\":\"https://lh3.googleusercontent.com/a/AAcHTteiDQp01uiXl-AJUADRisf4uPRbmZUwd7fNHAyq=s128-c0x00000000-cc-rp-mo-ba4\",\"rating\":5,\"relative_time_description\":\"a year ago\",\"text\":\"This is the best burger place in Jordan by far!\\nFries portion is enough for 2 so care when ordering\\nI don't recommend the Wagyu burger, it's too expensive. The classic burger is still as good even better.\\nAt least my opinion.\",\"time\":1653316121,\"translated\":false}],\"serves_beer\":false,\"serves_breakfast\":true,\"serves_brunch\":true,\"serves_dinner\":true,\"serves_lunch\":true,\"serves_wine\":false,\"takeout\":true,\"types\":[\"restaurant\",\"food\",\"point_of_interest\",\"establishment\"],\"url\":\"https://maps.google.com/?cid=13530507186889565808\",\"user_ratings_total\":814,\"utc_offset\":180,\"vicinity\":\"WVXC+XW8, Baalbeck, Amman\",\"website\":\"https://m.facebook.com/soulfoodjo/\"},\"status\":\"OK\"}",
      "inCount":1,
      "outCount":0,
      "isIn":null
    }
  ]
}